{
    "description": "",
    "tags": [],
    "size": {
        "height": 768,
        "width": 1024
    },
    "objects": [
        {
            "id": 953100386,
            "classId": 10169366,
            "description": "",
            "geometryType": "polygon",
            "labelerLogin": "NeginGh",
            "createdAt": "2022-06-13T09:49:26.776Z",
            "updatedAt": "2022-06-13T09:49:26.776Z",
            "tags": [],
            "classTitle": "Lens",
            "points": {
                "exterior": [
                    [
                        500,
                        265
                    ],
                    [
                        514,
                        254
                    ],
                    [
                        533,
                        247
                    ],
                    [
                        551,
                        243
                    ],
                    [
                        567,
                        244
                    ],
                    [
                        581,
                        245
                    ],
                    [
                        596,
                        238
                    ],
                    [
                        610,
                        224
                    ],
                    [
                        631,
                        232
                    ],
                    [
                        636,
                        244
                    ],
                    [
                        641,
                        256
                    ],
                    [
                        649,
                        273
                    ],
                    [
                        659,
                        288
                    ],
                    [
                        670,
                        301
                    ],
                    [
                        679,
                        319
                    ],
                    [
                        686,
                        338
                    ],
                    [
                        690,
                        360
                    ],
                    [
                        690,
                        382
                    ],
                    [
                        688,
                        401
                    ],
                    [
                        681,
                        417
                    ],
                    [
                        672,
                        433
                    ],
                    [
                        661,
                        448
                    ],
                    [
                        649,
                        460
                    ],
                    [
                        633,
                        472
                    ],
                    [
                        616,
                        481
                    ],
                    [
                        597,
                        486
                    ],
                    [
                        579,
                        488
                    ],
                    [
                        562,
                        487
                    ],
                    [
                        537,
                        506
                    ],
                    [
                        521,
                        503
                    ],
                    [
                        503,
                        496
                    ],
                    [
                        498,
                        474
                    ],
                    [
                        492,
                        457
                    ],
                    [
                        480,
                        446
                    ],
                    [
                        467,
                        428
                    ],
                    [
                        456,
                        405
                    ],
                    [
                        449,
                        378
                    ],
                    [
                        449,
                        353
                    ],
                    [
                        454,
                        332
                    ],
                    [
                        461,
                        314
                    ],
                    [
                        470,
                        296
                    ],
                    [
                        483,
                        280
                    ]
                ],
                "interior": []
            }
        },
        {
            "id": 953100387,
            "classId": 10169367,
            "description": "",
            "geometryType": "polygon",
            "labelerLogin": "NeginGh",
            "createdAt": "2022-06-13T09:49:26.776Z",
            "updatedAt": "2022-06-13T09:49:26.776Z",
            "tags": [],
            "classTitle": "Pupil",
            "points": {
                "exterior": [
                    [
                        522,
                        229
                    ],
                    [
                        539,
                        223
                    ],
                    [
                        563,
                        219
                    ],
                    [
                        584,
                        219
                    ],
                    [
                        601,
                        222
                    ],
                    [
                        620,
                        227
                    ],
                    [
                        639,
                        237
                    ],
                    [
                        656,
                        249
                    ],
                    [
                        670,
                        262
                    ],
                    [
                        685,
                        277
                    ],
                    [
                        697,
                        295
                    ],
                    [
                        707,
                        315
                    ],
                    [
                        714,
                        336
                    ],
                    [
                        719,
                        358
                    ],
                    [
                        720,
                        382
                    ],
                    [
                        719,
                        404
                    ],
                    [
                        713,
                        420
                    ],
                    [
                        705,
                        437
                    ],
                    [
                        694,
                        454
                    ],
                    [
                        682,
                        468
                    ],
                    [
                        664,
                        483
                    ],
                    [
                        644,
                        495
                    ],
                    [
                        624,
                        504
                    ],
                    [
                        605,
                        511
                    ],
                    [
                        580,
                        514
                    ],
                    [
                        558,
                        513
                    ],
                    [
                        539,
                        510
                    ],
                    [
                        521,
                        504
                    ],
                    [
                        504,
                        499
                    ],
                    [
                        484,
                        488
                    ],
                    [
                        469,
                        473
                    ],
                    [
                        456,
                        456
                    ],
                    [
                        441,
                        437
                    ],
                    [
                        431,
                        417
                    ],
                    [
                        426,
                        396
                    ],
                    [
                        423,
                        373
                    ],
                    [
                        424,
                        352
                    ],
                    [
                        427,
                        331
                    ],
                    [
                        435,
                        306
                    ],
                    [
                        445,
                        286
                    ],
                    [
                        458,
                        268
                    ],
                    [
                        473,
                        253
                    ],
                    [
                        488,
                        243
                    ],
                    [
                        505,
                        234
                    ]
                ],
                "interior": []
            }
        },
        {
            "id": 953100388,
            "classId": 10169368,
            "description": "",
            "geometryType": "polygon",
            "labelerLogin": "NeginGh",
            "createdAt": "2022-06-13T09:49:26.776Z",
            "updatedAt": "2022-06-13T09:49:26.776Z",
            "tags": [],
            "classTitle": "Cornea",
            "points": {
                "exterior": [
                    [
                        578,
                        163
                    ],
                    [
                        610,
                        167
                    ],
                    [
                        640,
                        176
                    ],
                    [
                        669,
                        190
                    ],
                    [
                        695,
                        208
                    ],
                    [
                        716,
                        226
                    ],
                    [
                        734,
                        245
                    ],
                    [
                        750,
                        268
                    ],
                    [
                        763,
                        293
                    ],
                    [
                        775,
                        324
                    ],
                    [
                        781,
                        350
                    ],
                    [
                        781,
                        383
                    ],
                    [
                        778,
                        408
                    ],
                    [
                        769,
                        435
                    ],
                    [
                        758,
                        460
                    ],
                    [
                        742,
                        482
                    ],
                    [
                        724,
                        501
                    ],
                    [
                        701,
                        517
                    ],
                    [
                        682,
                        528
                    ],
                    [
                        656,
                        541
                    ],
                    [
                        628,
                        550
                    ],
                    [
                        598,
                        554
                    ],
                    [
                        574,
                        555
                    ],
                    [
                        544,
                        554
                    ],
                    [
                        518,
                        550
                    ],
                    [
                        489,
                        541
                    ],
                    [
                        462,
                        531
                    ],
                    [
                        438,
                        517
                    ],
                    [
                        416,
                        495
                    ],
                    [
                        400,
                        473
                    ],
                    [
                        386,
                        450
                    ],
                    [
                        372,
                        424
                    ],
                    [
                        364,
                        392
                    ],
                    [
                        362,
                        362
                    ],
                    [
                        365,
                        329
                    ],
                    [
                        374,
                        299
                    ],
                    [
                        388,
                        273
                    ],
                    [
                        405,
                        247
                    ],
                    [
                        423,
                        225
                    ],
                    [
                        447,
                        206
                    ],
                    [
                        473,
                        188
                    ],
                    [
                        501,
                        175
                    ],
                    [
                        530,
                        167
                    ],
                    [
                        556,
                        164
                    ]
                ],
                "interior": []
            }
        }
    ]
}