{
    "description": "",
    "tags": [],
    "size": {
        "height": 768,
        "width": 1024
    },
    "objects": [
        {
            "id": 953097371,
            "classId": 10169370,
            "description": "",
            "geometryType": "polygon",
            "labelerLogin": "NeginGh",
            "createdAt": "2022-06-13T09:49:26.776Z",
            "updatedAt": "2022-06-13T09:49:26.776Z",
            "tags": [],
            "classTitle": "Gauge",
            "points": {
                "exterior": [
                    [
                        695,
                        767
                    ],
                    [
                        589,
                        568
                    ],
                    [
                        580,
                        553
                    ],
                    [
                        574,
                        544
                    ],
                    [
                        565,
                        538
                    ],
                    [
                        473,
                        488
                    ],
                    [
                        434,
                        465
                    ],
                    [
                        431,
                        459
                    ],
                    [
                        434,
                        452
                    ],
                    [
                        440,
                        449
                    ],
                    [
                        449,
                        452
                    ],
                    [
                        551,
                        515
                    ],
                    [
                        573,
                        527
                    ],
                    [
                        584,
                        535
                    ],
                    [
                        592,
                        540
                    ],
                    [
                        598,
                        550
                    ],
                    [
                        682,
                        710
                    ],
                    [
                        716,
                        767
                    ]
                ],
                "interior": []
            }
        },
        {
            "id": 953097372,
            "classId": 10169367,
            "description": "",
            "geometryType": "polygon",
            "labelerLogin": "NeginGh",
            "createdAt": "2022-06-13T09:49:26.776Z",
            "updatedAt": "2022-06-13T09:49:26.776Z",
            "tags": [],
            "classTitle": "Pupil",
            "points": {
                "exterior": [
                    [
                        509,
                        255
                    ],
                    [
                        535,
                        251
                    ],
                    [
                        558,
                        255
                    ],
                    [
                        580,
                        262
                    ],
                    [
                        603,
                        274
                    ],
                    [
                        622,
                        289
                    ],
                    [
                        639,
                        307
                    ],
                    [
                        653,
                        327
                    ],
                    [
                        660,
                        346
                    ],
                    [
                        666,
                        367
                    ],
                    [
                        668,
                        389
                    ],
                    [
                        669,
                        412
                    ],
                    [
                        667,
                        432
                    ],
                    [
                        658,
                        452
                    ],
                    [
                        648,
                        471
                    ],
                    [
                        635,
                        487
                    ],
                    [
                        619,
                        501
                    ],
                    [
                        600,
                        511
                    ],
                    [
                        578,
                        517
                    ],
                    [
                        560,
                        521
                    ],
                    [
                        536,
                        524
                    ],
                    [
                        517,
                        523
                    ],
                    [
                        496,
                        519
                    ],
                    [
                        475,
                        512
                    ],
                    [
                        455,
                        502
                    ],
                    [
                        435,
                        481
                    ],
                    [
                        423,
                        462
                    ],
                    [
                        412,
                        440
                    ],
                    [
                        406,
                        417
                    ],
                    [
                        402,
                        394
                    ],
                    [
                        406,
                        369
                    ],
                    [
                        411,
                        348
                    ],
                    [
                        423,
                        324
                    ],
                    [
                        440,
                        300
                    ],
                    [
                        455,
                        284
                    ],
                    [
                        474,
                        271
                    ],
                    [
                        491,
                        261
                    ]
                ],
                "interior": []
            }
        },
        {
            "id": 953097373,
            "classId": 10169368,
            "description": "",
            "geometryType": "polygon",
            "labelerLogin": "NeginGh",
            "createdAt": "2022-06-13T09:49:26.776Z",
            "updatedAt": "2022-06-13T09:49:26.776Z",
            "tags": [],
            "classTitle": "Cornea",
            "points": {
                "exterior": [
                    [
                        360,
                        305
                    ],
                    [
                        381,
                        278
                    ],
                    [
                        409,
                        251
                    ],
                    [
                        444,
                        229
                    ],
                    [
                        476,
                        214
                    ],
                    [
                        517,
                        204
                    ],
                    [
                        551,
                        200
                    ],
                    [
                        585,
                        205
                    ],
                    [
                        616,
                        218
                    ],
                    [
                        646,
                        237
                    ],
                    [
                        672,
                        261
                    ],
                    [
                        691,
                        285
                    ],
                    [
                        708,
                        313
                    ],
                    [
                        726,
                        351
                    ],
                    [
                        734,
                        387
                    ],
                    [
                        731,
                        424
                    ],
                    [
                        716,
                        461
                    ],
                    [
                        699,
                        491
                    ],
                    [
                        668,
                        519
                    ],
                    [
                        634,
                        543
                    ],
                    [
                        601,
                        555
                    ],
                    [
                        560,
                        560
                    ],
                    [
                        517,
                        562
                    ],
                    [
                        475,
                        556
                    ],
                    [
                        433,
                        545
                    ],
                    [
                        400,
                        522
                    ],
                    [
                        369,
                        494
                    ],
                    [
                        352,
                        467
                    ],
                    [
                        339,
                        430
                    ],
                    [
                        337,
                        393
                    ],
                    [
                        337,
                        363
                    ],
                    [
                        346,
                        333
                    ]
                ],
                "interior": []
            }
        }
    ]
}