{
    "description": "",
    "tags": [],
    "size": {
        "height": 768,
        "width": 1024
    },
    "objects": [
        {
            "id": 953099468,
            "classId": 10169374,
            "description": "",
            "geometryType": "polygon",
            "labelerLogin": "NeginGh",
            "createdAt": "2022-06-13T09:49:26.776Z",
            "updatedAt": "2022-06-13T09:49:26.776Z",
            "tags": [],
            "classTitle": "Irrigation-Aspiration",
            "points": {
                "exterior": [
                    [
                        638,
                        767
                    ],
                    [
                        519,
                        546
                    ],
                    [
                        509,
                        529
                    ],
                    [
                        505,
                        514
                    ],
                    [
                        509,
                        496
                    ],
                    [
                        520,
                        480
                    ],
                    [
                        528,
                        468
                    ],
                    [
                        538,
                        465
                    ],
                    [
                        549,
                        469
                    ],
                    [
                        553,
                        479
                    ],
                    [
                        550,
                        491
                    ],
                    [
                        546,
                        505
                    ],
                    [
                        558,
                        537
                    ],
                    [
                        680,
                        767
                    ]
                ],
                "interior": []
            }
        },
        {
            "id": 953099469,
            "classId": 10169367,
            "description": "",
            "geometryType": "polygon",
            "labelerLogin": "NeginGh",
            "createdAt": "2022-06-13T09:49:26.776Z",
            "updatedAt": "2022-06-13T09:49:26.776Z",
            "tags": [],
            "classTitle": "Pupil",
            "points": {
                "exterior": [
                    [
                        416,
                        339
                    ],
                    [
                        447,
                        330
                    ],
                    [
                        479,
                        325
                    ],
                    [
                        513,
                        327
                    ],
                    [
                        540,
                        335
                    ],
                    [
                        561,
                        349
                    ],
                    [
                        577,
                        371
                    ],
                    [
                        588,
                        398
                    ],
                    [
                        591,
                        438
                    ],
                    [
                        582,
                        470
                    ],
                    [
                        568,
                        498
                    ],
                    [
                        550,
                        525
                    ],
                    [
                        526,
                        544
                    ],
                    [
                        500,
                        555
                    ],
                    [
                        467,
                        560
                    ],
                    [
                        432,
                        555
                    ],
                    [
                        396,
                        540
                    ],
                    [
                        371,
                        518
                    ],
                    [
                        355,
                        486
                    ],
                    [
                        345,
                        450
                    ],
                    [
                        350,
                        414
                    ],
                    [
                        360,
                        384
                    ],
                    [
                        385,
                        357
                    ]
                ],
                "interior": []
            }
        },
        {
            "id": 953099583,
            "classId": 10169368,
            "description": "",
            "geometryType": "polygon",
            "labelerLogin": "NeginGh",
            "createdAt": "2022-06-13T09:49:26.776Z",
            "updatedAt": "2022-06-13T09:49:26.776Z",
            "tags": [],
            "classTitle": "Cornea",
            "points": {
                "exterior": [
                    [
                        622,
                        289
                    ],
                    [
                        646,
                        315
                    ],
                    [
                        659,
                        336
                    ],
                    [
                        670,
                        367
                    ],
                    [
                        674,
                        397
                    ],
                    [
                        674,
                        430
                    ],
                    [
                        669,
                        456
                    ],
                    [
                        660,
                        487
                    ],
                    [
                        645,
                        515
                    ],
                    [
                        628,
                        539
                    ],
                    [
                        612,
                        559
                    ],
                    [
                        593,
                        575
                    ],
                    [
                        574,
                        589
                    ],
                    [
                        550,
                        601
                    ],
                    [
                        523,
                        609
                    ],
                    [
                        492,
                        614
                    ],
                    [
                        464,
                        615
                    ],
                    [
                        428,
                        614
                    ],
                    [
                        398,
                        610
                    ],
                    [
                        373,
                        600
                    ],
                    [
                        351,
                        588
                    ],
                    [
                        329,
                        572
                    ],
                    [
                        308,
                        550
                    ],
                    [
                        295,
                        523
                    ],
                    [
                        285,
                        491
                    ],
                    [
                        282,
                        458
                    ],
                    [
                        285,
                        427
                    ],
                    [
                        294,
                        400
                    ],
                    [
                        311,
                        373
                    ],
                    [
                        328,
                        349
                    ],
                    [
                        347,
                        325
                    ],
                    [
                        365,
                        306
                    ],
                    [
                        389,
                        289
                    ],
                    [
                        412,
                        273
                    ],
                    [
                        438,
                        261
                    ],
                    [
                        464,
                        253
                    ],
                    [
                        493,
                        248
                    ],
                    [
                        523,
                        248
                    ],
                    [
                        551,
                        253
                    ],
                    [
                        575,
                        261
                    ],
                    [
                        600,
                        273
                    ]
                ],
                "interior": []
            }
        }
    ]
}