{
    "description": "",
    "tags": [],
    "size": {
        "height": 768,
        "width": 1024
    },
    "objects": [
        {
            "id": 953099486,
            "classId": 10169367,
            "description": "",
            "geometryType": "polygon",
            "labelerLogin": "NeginGh",
            "createdAt": "2022-06-13T09:49:26.776Z",
            "updatedAt": "2022-06-13T09:49:26.776Z",
            "tags": [],
            "classTitle": "Pupil",
            "points": {
                "exterior": [
                    [
                        400,
                        295
                    ],
                    [
                        425,
                        290
                    ],
                    [
                        451,
                        291
                    ],
                    [
                        477,
                        295
                    ],
                    [
                        503,
                        302
                    ],
                    [
                        523,
                        314
                    ],
                    [
                        540,
                        331
                    ],
                    [
                        551,
                        350
                    ],
                    [
                        560,
                        372
                    ],
                    [
                        564,
                        399
                    ],
                    [
                        561,
                        424
                    ],
                    [
                        553,
                        450
                    ],
                    [
                        541,
                        476
                    ],
                    [
                        523,
                        496
                    ],
                    [
                        498,
                        511
                    ],
                    [
                        472,
                        522
                    ],
                    [
                        445,
                        527
                    ],
                    [
                        422,
                        525
                    ],
                    [
                        396,
                        518
                    ],
                    [
                        370,
                        506
                    ],
                    [
                        353,
                        490
                    ],
                    [
                        337,
                        467
                    ],
                    [
                        330,
                        446
                    ],
                    [
                        328,
                        415
                    ],
                    [
                        330,
                        389
                    ],
                    [
                        333,
                        361
                    ],
                    [
                        341,
                        338
                    ],
                    [
                        356,
                        319
                    ],
                    [
                        378,
                        305
                    ]
                ],
                "interior": []
            }
        },
        {
            "id": 953099487,
            "classId": 10169368,
            "description": "",
            "geometryType": "polygon",
            "labelerLogin": "NeginGh",
            "createdAt": "2022-06-13T09:49:26.776Z",
            "updatedAt": "2022-06-13T09:49:26.776Z",
            "tags": [],
            "classTitle": "Cornea",
            "points": {
                "exterior": [
                    [
                        356,
                        216
                    ],
                    [
                        391,
                        203
                    ],
                    [
                        433,
                        194
                    ],
                    [
                        477,
                        196
                    ],
                    [
                        521,
                        204
                    ],
                    [
                        556,
                        218
                    ],
                    [
                        589,
                        239
                    ],
                    [
                        617,
                        272
                    ],
                    [
                        634,
                        301
                    ],
                    [
                        649,
                        339
                    ],
                    [
                        656,
                        374
                    ],
                    [
                        655,
                        419
                    ],
                    [
                        643,
                        461
                    ],
                    [
                        625,
                        497
                    ],
                    [
                        599,
                        527
                    ],
                    [
                        574,
                        551
                    ],
                    [
                        539,
                        573
                    ],
                    [
                        496,
                        590
                    ],
                    [
                        456,
                        595
                    ],
                    [
                        414,
                        592
                    ],
                    [
                        376,
                        583
                    ],
                    [
                        340,
                        569
                    ],
                    [
                        304,
                        548
                    ],
                    [
                        274,
                        515
                    ],
                    [
                        249,
                        473
                    ],
                    [
                        235,
                        433
                    ],
                    [
                        230,
                        393
                    ],
                    [
                        244,
                        351
                    ],
                    [
                        267,
                        311
                    ],
                    [
                        292,
                        274
                    ],
                    [
                        321,
                        243
                    ]
                ],
                "interior": []
            }
        }
    ]
}