{
    "description": "",
    "tags": [],
    "size": {
        "height": 768,
        "width": 1024
    },
    "objects": [
        {
            "id": 953102868,
            "classId": 10169381,
            "description": "",
            "geometryType": "polygon",
            "labelerLogin": "NeginGh",
            "createdAt": "2022-06-13T09:49:44.770Z",
            "updatedAt": "2022-06-13T09:49:44.770Z",
            "tags": [],
            "classTitle": "Lens",
            "points": {
                "exterior": [
                    [
                        401,
                        327
                    ],
                    [
                        397,
                        316
                    ],
                    [
                        410,
                        301
                    ],
                    [
                        423,
                        289
                    ],
                    [
                        444,
                        280
                    ],
                    [
                        457,
                        276
                    ],
                    [
                        465,
                        274
                    ],
                    [
                        471,
                        271
                    ],
                    [
                        480,
                        272
                    ],
                    [
                        495,
                        293
                    ],
                    [
                        514,
                        317
                    ],
                    [
                        534,
                        346
                    ],
                    [
                        549,
                        368
                    ],
                    [
                        565,
                        393
                    ],
                    [
                        576,
                        412
                    ],
                    [
                        589,
                        422
                    ],
                    [
                        596,
                        433
                    ],
                    [
                        595,
                        448
                    ],
                    [
                        588,
                        465
                    ],
                    [
                        573,
                        474
                    ],
                    [
                        560,
                        480
                    ],
                    [
                        563,
                        496
                    ],
                    [
                        563,
                        513
                    ],
                    [
                        563,
                        524
                    ],
                    [
                        560,
                        536
                    ],
                    [
                        554,
                        539
                    ],
                    [
                        544,
                        541
                    ],
                    [
                        529,
                        528
                    ],
                    [
                        522,
                        511
                    ],
                    [
                        517,
                        498
                    ],
                    [
                        515,
                        486
                    ],
                    [
                        503,
                        475
                    ],
                    [
                        490,
                        454
                    ],
                    [
                        468,
                        430
                    ],
                    [
                        454,
                        407
                    ],
                    [
                        436,
                        382
                    ],
                    [
                        421,
                        360
                    ],
                    [
                        408,
                        342
                    ]
                ],
                "interior": []
            }
        },
        {
            "id": 953102869,
            "classId": 10169382,
            "description": "",
            "geometryType": "polygon",
            "labelerLogin": "NeginGh",
            "createdAt": "2022-06-13T09:49:44.770Z",
            "updatedAt": "2022-06-13T09:49:44.770Z",
            "tags": [],
            "classTitle": "Pupil",
            "points": {
                "exterior": [
                    [
                        531,
                        270
                    ],
                    [
                        553,
                        280
                    ],
                    [
                        578,
                        298
                    ],
                    [
                        596,
                        319
                    ],
                    [
                        611,
                        337
                    ],
                    [
                        620,
                        356
                    ],
                    [
                        628,
                        377
                    ],
                    [
                        633,
                        397
                    ],
                    [
                        630,
                        422
                    ],
                    [
                        622,
                        441
                    ],
                    [
                        612,
                        458
                    ],
                    [
                        603,
                        471
                    ],
                    [
                        587,
                        486
                    ],
                    [
                        569,
                        502
                    ],
                    [
                        541,
                        513
                    ],
                    [
                        514,
                        519
                    ],
                    [
                        476,
                        517
                    ],
                    [
                        456,
                        513
                    ],
                    [
                        434,
                        502
                    ],
                    [
                        414,
                        487
                    ],
                    [
                        399,
                        473
                    ],
                    [
                        382,
                        447
                    ],
                    [
                        377,
                        422
                    ],
                    [
                        375,
                        389
                    ],
                    [
                        381,
                        354
                    ],
                    [
                        389,
                        334
                    ],
                    [
                        398,
                        317
                    ],
                    [
                        406,
                        305
                    ],
                    [
                        420,
                        290
                    ],
                    [
                        437,
                        279
                    ],
                    [
                        464,
                        272
                    ],
                    [
                        489,
                        267
                    ],
                    [
                        512,
                        266
                    ]
                ],
                "interior": []
            }
        },
        {
            "id": 953103187,
            "classId": 10169383,
            "description": "",
            "geometryType": "polygon",
            "labelerLogin": "NeginGh",
            "createdAt": "2022-06-13T09:49:44.770Z",
            "updatedAt": "2022-06-13T09:49:44.770Z",
            "tags": [],
            "classTitle": "Cornea",
            "points": {
                "exterior": [
                    [
                        461,
                        201
                    ],
                    [
                        494,
                        194
                    ],
                    [
                        536,
                        196
                    ],
                    [
                        576,
                        201
                    ],
                    [
                        605,
                        216
                    ],
                    [
                        635,
                        236
                    ],
                    [
                        662,
                        260
                    ],
                    [
                        680,
                        288
                    ],
                    [
                        695,
                        324
                    ],
                    [
                        705,
                        354
                    ],
                    [
                        712,
                        392
                    ],
                    [
                        709,
                        427
                    ],
                    [
                        697,
                        458
                    ],
                    [
                        681,
                        487
                    ],
                    [
                        663,
                        509
                    ],
                    [
                        642,
                        528
                    ],
                    [
                        622,
                        542
                    ],
                    [
                        596,
                        555
                    ],
                    [
                        564,
                        566
                    ],
                    [
                        530,
                        569
                    ],
                    [
                        499,
                        571
                    ],
                    [
                        461,
                        568
                    ],
                    [
                        424,
                        559
                    ],
                    [
                        394,
                        548
                    ],
                    [
                        370,
                        530
                    ],
                    [
                        347,
                        505
                    ],
                    [
                        328,
                        482
                    ],
                    [
                        309,
                        448
                    ],
                    [
                        303,
                        416
                    ],
                    [
                        301,
                        383
                    ],
                    [
                        310,
                        346
                    ],
                    [
                        320,
                        313
                    ],
                    [
                        342,
                        283
                    ],
                    [
                        367,
                        257
                    ],
                    [
                        396,
                        235
                    ],
                    [
                        437,
                        213
                    ]
                ],
                "interior": []
            }
        }
    ]
}