{
    "description": "",
    "tags": [],
    "size": {
        "height": 768,
        "width": 1024
    },
    "objects": [
        {
            "id": 953102721,
            "classId": 10169387,
            "description": "",
            "geometryType": "polygon",
            "labelerLogin": "NeginGh",
            "createdAt": "2022-06-13T09:49:44.770Z",
            "updatedAt": "2022-06-13T09:49:44.770Z",
            "tags": [],
            "classTitle": "Gauge",
            "points": {
                "exterior": [
                    [
                        791,
                        767
                    ],
                    [
                        733,
                        672
                    ],
                    [
                        681,
                        589
                    ],
                    [
                        651,
                        542
                    ],
                    [
                        639,
                        518
                    ],
                    [
                        642,
                        510
                    ],
                    [
                        649,
                        508
                    ],
                    [
                        695,
                        583
                    ],
                    [
                        814,
                        767
                    ]
                ],
                "interior": []
            }
        },
        {
            "id": 953102722,
            "classId": 10169382,
            "description": "",
            "geometryType": "polygon",
            "labelerLogin": "NeginGh",
            "createdAt": "2022-06-13T09:49:44.770Z",
            "updatedAt": "2022-06-13T09:49:44.770Z",
            "tags": [],
            "classTitle": "Pupil",
            "points": {
                "exterior": [
                    [
                        490,
                        215
                    ],
                    [
                        514,
                        222
                    ],
                    [
                        539,
                        236
                    ],
                    [
                        560,
                        248
                    ],
                    [
                        586,
                        258
                    ],
                    [
                        612,
                        276
                    ],
                    [
                        631,
                        294
                    ],
                    [
                        643,
                        310
                    ],
                    [
                        647,
                        336
                    ],
                    [
                        648,
                        364
                    ],
                    [
                        637,
                        384
                    ],
                    [
                        626,
                        411
                    ],
                    [
                        612,
                        427
                    ],
                    [
                        593,
                        441
                    ],
                    [
                        572,
                        453
                    ],
                    [
                        554,
                        461
                    ],
                    [
                        527,
                        464
                    ],
                    [
                        503,
                        462
                    ],
                    [
                        480,
                        456
                    ],
                    [
                        460,
                        446
                    ],
                    [
                        438,
                        437
                    ],
                    [
                        422,
                        419
                    ],
                    [
                        409,
                        400
                    ],
                    [
                        400,
                        375
                    ],
                    [
                        396,
                        346
                    ],
                    [
                        396,
                        323
                    ],
                    [
                        401,
                        297
                    ],
                    [
                        409,
                        273
                    ],
                    [
                        419,
                        255
                    ],
                    [
                        433,
                        240
                    ],
                    [
                        452,
                        226
                    ],
                    [
                        470,
                        217
                    ],
                    [
                        479,
                        213
                    ]
                ],
                "interior": []
            }
        },
        {
            "id": 953102723,
            "classId": 10169383,
            "description": "",
            "geometryType": "polygon",
            "labelerLogin": "NeginGh",
            "createdAt": "2022-06-13T09:49:44.770Z",
            "updatedAt": "2022-06-13T09:49:44.770Z",
            "tags": [],
            "classTitle": "Cornea",
            "points": {
                "exterior": [
                    [
                        696,
                        227
                    ],
                    [
                        718,
                        258
                    ],
                    [
                        726,
                        288
                    ],
                    [
                        736,
                        318
                    ],
                    [
                        737,
                        350
                    ],
                    [
                        729,
                        376
                    ],
                    [
                        720,
                        407
                    ],
                    [
                        698,
                        445
                    ],
                    [
                        659,
                        478
                    ],
                    [
                        635,
                        495
                    ],
                    [
                        595,
                        511
                    ],
                    [
                        550,
                        515
                    ],
                    [
                        508,
                        513
                    ],
                    [
                        470,
                        512
                    ],
                    [
                        434,
                        495
                    ],
                    [
                        407,
                        477
                    ],
                    [
                        379,
                        451
                    ],
                    [
                        353,
                        423
                    ],
                    [
                        336,
                        399
                    ],
                    [
                        326,
                        369
                    ],
                    [
                        322,
                        338
                    ],
                    [
                        330,
                        293
                    ],
                    [
                        343,
                        256
                    ],
                    [
                        359,
                        230
                    ],
                    [
                        375,
                        209
                    ],
                    [
                        402,
                        185
                    ],
                    [
                        420,
                        168
                    ],
                    [
                        441,
                        155
                    ],
                    [
                        468,
                        149
                    ],
                    [
                        506,
                        145
                    ],
                    [
                        538,
                        144
                    ],
                    [
                        565,
                        141
                    ],
                    [
                        594,
                        145
                    ],
                    [
                        624,
                        157
                    ],
                    [
                        656,
                        179
                    ],
                    [
                        680,
                        204
                    ]
                ],
                "interior": []
            }
        }
    ]
}