{
    "description": "",
    "tags": [],
    "size": {
        "height": 768,
        "width": 1024
    },
    "objects": [
        {
            "id": 953102768,
            "classId": 10169382,
            "description": "",
            "geometryType": "polygon",
            "labelerLogin": "NeginGh",
            "createdAt": "2022-06-13T09:49:44.770Z",
            "updatedAt": "2022-06-13T09:49:44.770Z",
            "tags": [],
            "classTitle": "Pupil",
            "points": {
                "exterior": [
                    [
                        632,
                        267
                    ],
                    [
                        642,
                        288
                    ],
                    [
                        653,
                        318
                    ],
                    [
                        657,
                        343
                    ],
                    [
                        653,
                        371
                    ],
                    [
                        645,
                        396
                    ],
                    [
                        632,
                        418
                    ],
                    [
                        617,
                        434
                    ],
                    [
                        599,
                        448
                    ],
                    [
                        579,
                        457
                    ],
                    [
                        560,
                        466
                    ],
                    [
                        541,
                        469
                    ],
                    [
                        512,
                        468
                    ],
                    [
                        485,
                        461
                    ],
                    [
                        462,
                        453
                    ],
                    [
                        443,
                        439
                    ],
                    [
                        426,
                        419
                    ],
                    [
                        413,
                        393
                    ],
                    [
                        408,
                        368
                    ],
                    [
                        407,
                        344
                    ],
                    [
                        408,
                        321
                    ],
                    [
                        416,
                        297
                    ],
                    [
                        424,
                        275
                    ],
                    [
                        429,
                        258
                    ],
                    [
                        436,
                        245
                    ],
                    [
                        448,
                        229
                    ],
                    [
                        465,
                        220
                    ],
                    [
                        486,
                        211
                    ],
                    [
                        507,
                        209
                    ],
                    [
                        532,
                        215
                    ],
                    [
                        553,
                        215
                    ],
                    [
                        572,
                        224
                    ],
                    [
                        592,
                        233
                    ],
                    [
                        615,
                        251
                    ]
                ],
                "interior": []
            }
        },
        {
            "id": 953102769,
            "classId": 10169383,
            "description": "",
            "geometryType": "polygon",
            "labelerLogin": "NeginGh",
            "createdAt": "2022-06-13T09:49:44.770Z",
            "updatedAt": "2022-06-13T09:49:44.770Z",
            "tags": [],
            "classTitle": "Cornea",
            "points": {
                "exterior": [
                    [
                        721,
                        270
                    ],
                    [
                        735,
                        304
                    ],
                    [
                        741,
                        339
                    ],
                    [
                        737,
                        373
                    ],
                    [
                        724,
                        400
                    ],
                    [
                        707,
                        436
                    ],
                    [
                        687,
                        464
                    ],
                    [
                        665,
                        486
                    ],
                    [
                        624,
                        515
                    ],
                    [
                        582,
                        522
                    ],
                    [
                        540,
                        525
                    ],
                    [
                        494,
                        519
                    ],
                    [
                        461,
                        509
                    ],
                    [
                        431,
                        497
                    ],
                    [
                        402,
                        474
                    ],
                    [
                        376,
                        449
                    ],
                    [
                        357,
                        428
                    ],
                    [
                        340,
                        396
                    ],
                    [
                        332,
                        370
                    ],
                    [
                        331,
                        332
                    ],
                    [
                        334,
                        302
                    ],
                    [
                        344,
                        275
                    ],
                    [
                        360,
                        249
                    ],
                    [
                        380,
                        223
                    ],
                    [
                        406,
                        195
                    ],
                    [
                        431,
                        175
                    ],
                    [
                        458,
                        159
                    ],
                    [
                        491,
                        149
                    ],
                    [
                        523,
                        147
                    ],
                    [
                        551,
                        146
                    ],
                    [
                        581,
                        147
                    ],
                    [
                        611,
                        155
                    ],
                    [
                        652,
                        177
                    ],
                    [
                        680,
                        202
                    ],
                    [
                        702,
                        233
                    ],
                    [
                        714,
                        255
                    ]
                ],
                "interior": []
            }
        }
    ]
}