{
    "description": "",
    "tags": [],
    "size": {
        "height": 768,
        "width": 1024
    },
    "objects": [
        {
            "id": 953102937,
            "classId": 10169385,
            "description": "",
            "geometryType": "polygon",
            "labelerLogin": "NeginGh",
            "createdAt": "2022-06-13T09:49:44.770Z",
            "updatedAt": "2022-06-13T09:49:44.770Z",
            "tags": [],
            "classTitle": "Spatula",
            "points": {
                "exterior": [
                    [
                        583,
                        767
                    ],
                    [
                        589,
                        732
                    ],
                    [
                        601,
                        684
                    ],
                    [
                        611,
                        646
                    ],
                    [
                        613,
                        621
                    ],
                    [
                        617,
                        598
                    ],
                    [
                        623,
                        581
                    ],
                    [
                        626,
                        569
                    ],
                    [
                        633,
                        568
                    ],
                    [
                        640,
                        571
                    ],
                    [
                        641,
                        583
                    ],
                    [
                        635,
                        623
                    ],
                    [
                        621,
                        683
                    ],
                    [
                        615,
                        717
                    ],
                    [
                        605,
                        767
                    ]
                ],
                "interior": []
            }
        },
        {
            "id": 953102938,
            "classId": 10169382,
            "description": "",
            "geometryType": "polygon",
            "labelerLogin": "NeginGh",
            "createdAt": "2022-06-13T09:49:44.770Z",
            "updatedAt": "2022-06-13T09:49:44.770Z",
            "tags": [],
            "classTitle": "Pupil",
            "points": {
                "exterior": [
                    [
                        591,
                        239
                    ],
                    [
                        606,
                        254
                    ],
                    [
                        619,
                        272
                    ],
                    [
                        630,
                        287
                    ],
                    [
                        636,
                        301
                    ],
                    [
                        640,
                        318
                    ],
                    [
                        642,
                        337
                    ],
                    [
                        642,
                        353
                    ],
                    [
                        637,
                        370
                    ],
                    [
                        630,
                        388
                    ],
                    [
                        621,
                        403
                    ],
                    [
                        610,
                        417
                    ],
                    [
                        596,
                        431
                    ],
                    [
                        582,
                        442
                    ],
                    [
                        563,
                        452
                    ],
                    [
                        526,
                        462
                    ],
                    [
                        501,
                        462
                    ],
                    [
                        480,
                        459
                    ],
                    [
                        456,
                        451
                    ],
                    [
                        440,
                        439
                    ],
                    [
                        420,
                        424
                    ],
                    [
                        407,
                        408
                    ],
                    [
                        395,
                        390
                    ],
                    [
                        389,
                        367
                    ],
                    [
                        389,
                        347
                    ],
                    [
                        388,
                        326
                    ],
                    [
                        391,
                        298
                    ],
                    [
                        400,
                        275
                    ],
                    [
                        414,
                        255
                    ],
                    [
                        433,
                        237
                    ],
                    [
                        450,
                        223
                    ],
                    [
                        470,
                        212
                    ],
                    [
                        492,
                        207
                    ],
                    [
                        516,
                        206
                    ],
                    [
                        536,
                        211
                    ],
                    [
                        557,
                        217
                    ],
                    [
                        578,
                        228
                    ]
                ],
                "interior": []
            }
        },
        {
            "id": 953102939,
            "classId": 10169383,
            "description": "",
            "geometryType": "polygon",
            "labelerLogin": "NeginGh",
            "createdAt": "2022-06-13T09:49:44.770Z",
            "updatedAt": "2022-06-13T09:49:44.770Z",
            "tags": [],
            "classTitle": "Cornea",
            "points": {
                "exterior": [
                    [
                        713,
                        258
                    ],
                    [
                        722,
                        293
                    ],
                    [
                        726,
                        332
                    ],
                    [
                        722,
                        361
                    ],
                    [
                        711,
                        391
                    ],
                    [
                        701,
                        417
                    ],
                    [
                        686,
                        440
                    ],
                    [
                        668,
                        464
                    ],
                    [
                        643,
                        488
                    ],
                    [
                        618,
                        504
                    ],
                    [
                        595,
                        513
                    ],
                    [
                        564,
                        520
                    ],
                    [
                        522,
                        525
                    ],
                    [
                        482,
                        521
                    ],
                    [
                        450,
                        508
                    ],
                    [
                        406,
                        481
                    ],
                    [
                        377,
                        456
                    ],
                    [
                        354,
                        426
                    ],
                    [
                        333,
                        386
                    ],
                    [
                        322,
                        347
                    ],
                    [
                        322,
                        305
                    ],
                    [
                        331,
                        265
                    ],
                    [
                        349,
                        233
                    ],
                    [
                        373,
                        204
                    ],
                    [
                        398,
                        180
                    ],
                    [
                        426,
                        162
                    ],
                    [
                        460,
                        146
                    ],
                    [
                        492,
                        137
                    ],
                    [
                        527,
                        133
                    ],
                    [
                        555,
                        134
                    ],
                    [
                        586,
                        142
                    ],
                    [
                        616,
                        157
                    ],
                    [
                        645,
                        173
                    ],
                    [
                        671,
                        198
                    ],
                    [
                        689,
                        224
                    ]
                ],
                "interior": []
            }
        }
    ]
}