{
    "description": "",
    "tags": [],
    "size": {
        "height": 768,
        "width": 1024
    },
    "objects": [
        {
            "id": 953099768,
            "classId": 10169367,
            "description": "",
            "geometryType": "polygon",
            "labelerLogin": "NeginGh",
            "createdAt": "2022-06-13T09:49:26.776Z",
            "updatedAt": "2022-06-13T09:49:26.776Z",
            "tags": [],
            "classTitle": "Pupil",
            "points": {
                "exterior": [
                    [
                        515,
                        324
                    ],
                    [
                        540,
                        305
                    ],
                    [
                        574,
                        288
                    ],
                    [
                        607,
                        278
                    ],
                    [
                        644,
                        278
                    ],
                    [
                        679,
                        284
                    ],
                    [
                        711,
                        295
                    ],
                    [
                        736,
                        310
                    ],
                    [
                        757,
                        332
                    ],
                    [
                        776,
                        364
                    ],
                    [
                        790,
                        397
                    ],
                    [
                        794,
                        434
                    ],
                    [
                        790,
                        471
                    ],
                    [
                        774,
                        510
                    ],
                    [
                        753,
                        540
                    ],
                    [
                        728,
                        563
                    ],
                    [
                        696,
                        584
                    ],
                    [
                        663,
                        595
                    ],
                    [
                        626,
                        601
                    ],
                    [
                        588,
                        597
                    ],
                    [
                        554,
                        587
                    ],
                    [
                        524,
                        565
                    ],
                    [
                        500,
                        536
                    ],
                    [
                        486,
                        505
                    ],
                    [
                        471,
                        463
                    ],
                    [
                        471,
                        420
                    ],
                    [
                        481,
                        382
                    ],
                    [
                        495,
                        350
                    ]
                ],
                "interior": []
            }
        },
        {
            "id": 953099769,
            "classId": 10169368,
            "description": "",
            "geometryType": "polygon",
            "labelerLogin": "NeginGh",
            "createdAt": "2022-06-13T09:49:26.776Z",
            "updatedAt": "2022-06-13T09:49:26.776Z",
            "tags": [],
            "classTitle": "Cornea",
            "points": {
                "exterior": [
                    [
                        460,
                        298
                    ],
                    [
                        483,
                        274
                    ],
                    [
                        515,
                        250
                    ],
                    [
                        550,
                        230
                    ],
                    [
                        591,
                        219
                    ],
                    [
                        631,
                        217
                    ],
                    [
                        671,
                        220
                    ],
                    [
                        712,
                        232
                    ],
                    [
                        748,
                        247
                    ],
                    [
                        783,
                        272
                    ],
                    [
                        806,
                        301
                    ],
                    [
                        823,
                        335
                    ],
                    [
                        836,
                        377
                    ],
                    [
                        845,
                        423
                    ],
                    [
                        846,
                        466
                    ],
                    [
                        838,
                        503
                    ],
                    [
                        811,
                        538
                    ],
                    [
                        785,
                        571
                    ],
                    [
                        750,
                        604
                    ],
                    [
                        720,
                        622
                    ],
                    [
                        679,
                        632
                    ],
                    [
                        628,
                        637
                    ],
                    [
                        578,
                        633
                    ],
                    [
                        536,
                        623
                    ],
                    [
                        492,
                        601
                    ],
                    [
                        456,
                        574
                    ],
                    [
                        429,
                        533
                    ],
                    [
                        417,
                        487
                    ],
                    [
                        411,
                        437
                    ],
                    [
                        415,
                        393
                    ],
                    [
                        429,
                        350
                    ],
                    [
                        444,
                        320
                    ]
                ],
                "interior": []
            }
        }
    ]
}